formatting/__init__.py
formatting/apa.py
labels/__init__.py
labels/apa.py
names/__init__.py
names/firstlast.py
pybtex_apa7_style-0.1.3.dist-info/entry_points.txt
pybtex_apa7_style-0.1.3.dist-info/LICENSE
pybtex_apa7_style-0.1.3.dist-info/WHEEL
pybtex_apa7_style-0.1.3.dist-info/METADATA
pybtex_apa7_style-0.1.3.dist-info/RECORD
