Metadata-Version: 2.1
Name: pybtex-apa7-style
Version: 0.1.3
Summary: Provides APA7 style for Pybtex
Home-page: https://github.com/cproctor/pybtex-apa7-style
License: MIT
Author: Chris Proctor
Author-email: github.com@accounts.chrisproctor.net
Requires-Python: >=3.9,<4.0
Classifier: License :: OSI Approved :: MIT License
Classifier: Operating System :: OS Independent
Classifier: Programming Language :: Python
Classifier: Programming Language :: Python :: 3
Classifier: Programming Language :: Python :: 3.10
Classifier: Programming Language :: Python :: 3.9
Classifier: Topic :: Text Processing :: Markup
Classifier: Topic :: Utilities
Requires-Dist: pybtex (>=0.24.0,<0.25.0)
Project-URL: Repository, https://github.com/cproctor/pybtex-apa7-style
